README.md
setup.cfg
setup.py
PM/PMmodule.c
PM/__init__.py
PM/pm_encrypt.c
PMteam.egg-info/PKG-INFO
PMteam.egg-info/SOURCES.txt
PMteam.egg-info/dependency_links.txt
PMteam.egg-info/top_level.txt